zeroshot_topics/__init__.py
zeroshot_topics/utils.py
zeroshot_topics/zeroshot_tm.py
zeroshot_topics-0.1.0.dist-info/LICENSE-APACHE
zeroshot_topics-0.1.0.dist-info/LICENSE-MIT
zeroshot_topics-0.1.0.dist-info/METADATA
zeroshot_topics-0.1.0.dist-info/WHEEL
zeroshot_topics-0.1.0.dist-info/top_level.txt
zeroshot_topics-0.1.0.dist-info/RECORD
